pycoolmasternet_async/__init__.py
pycoolmasternet_async/coolmasternet.py
pycoolmasternet_async-0.2.3.dist-info/licenses/LICENSE
pycoolmasternet_async-0.2.3.dist-info/METADATA
pycoolmasternet_async-0.2.3.dist-info/WHEEL
pycoolmasternet_async-0.2.3.dist-info/top_level.txt
pycoolmasternet_async-0.2.3.dist-info/RECORD
