Metadata-Version: 2.4
Name: pycoolmasternet-async
Version: 0.2.3
Summary: A python library to control CoolMasterNet HVAC bridges over asyncio.
Home-page: https://github.com/OnFreund/pycoolmasternet-async
Author: On Freund
Author-email: onfreund@gmail.com
License: MIT
Classifier: License :: OSI Approved :: MIT License
Classifier: Programming Language :: Python
Classifier: Programming Language :: Python :: 3
Classifier: Programming Language :: Python :: 3.7
Classifier: Programming Language :: Python :: Implementation :: CPython
Classifier: Programming Language :: Python :: Implementation :: PyPy
Requires-Python: >=3.7.0
License-File: LICENSE
Dynamic: author
Dynamic: author-email
Dynamic: classifier
Dynamic: description
Dynamic: description-content-type
Dynamic: home-page
Dynamic: license
Dynamic: license-file
Dynamic: requires-python
Dynamic: summary
